<?xml version="1.0" encoding="utf-8" ?>
<records>
    <employee>
        <name>Sairam</name>
        <surname>Mamh</surname>
        <salary>50000</salary>
    </employee>

    <employee>
        <name>Gopal </name>
        <surname>Varma</surname>
        <salary>60000</salary>
    </employee>

    <employee>
        <name>Raja</name>
        <surname>Hr</surname>
        <salary>70000</salary>
    </employee>

    <employee>
        <name>Rajan</name>
        <surname>Hrrrr</surname>
        <salary>70000</salary>
    </employee>

</records>